harmoni/extratools.py
harmoni/harmonitools.py
harmoni-0.0.5.dist-info/LICENSE
harmoni-0.0.5.dist-info/METADATA
harmoni-0.0.5.dist-info/WHEEL
harmoni-0.0.5.dist-info/top_level.txt
harmoni-0.0.5.dist-info/RECORD
