Metadata-Version: 2.1
Name: harmoni
Version: 0.0.5
Summary: harmonic minimization method for eliminating harmonic-driven connectivity with MEEG
Home-page: https://github.com/harmonic-minimization/harmoni
Author: Mina Jamshidi
Author-email: minajamshidi91@gmail.com
License: UNKNOWN
Platform: UNKNOWN
Classifier: Programming Language :: Python :: 3.6
Classifier: License :: OSI Approved
Classifier: Operating System :: OS Independent
License-File: LICENSE
Requires-Dist: numpy (>=1.10)
Requires-Dist: scipy (>=0.19)
Provides-Extra: dev
Requires-Dist: pytest (>=6.2) ; extra == 'dev'
Requires-Dist: pytest-cov (>=2.12) ; extra == 'dev'
Requires-Dist: check-manifest (>=0.40) ; extra == 'dev'
Requires-Dist: flake8 (>=3.9.2) ; extra == 'dev'
Requires-Dist: mypy (>=0.910) ; extra == 'dev'
Requires-Dist: tox (>=3.24) ; extra == 'dev'
